README.md
setup.cfg
setup.py
eis/__init__.py
eis/claim/__init__.py
eis/claim/api_client.py
eis/claim/configuration.py
eis/claim/exceptions.py
eis/claim/model_utils.py
eis/claim/rest.py
eis/claim/api/__init__.py
eis/claim/api/claim_partner_roles_api.py
eis/claim/api/claim_partners_api.py
eis/claim/api/claim_regulations_api.py
eis/claim/api/claim_statuses_api.py
eis/claim/api/claims_api.py
eis/claim/api/health_check_api.py
eis/claim/api/settlements_api.py
eis/claim/apis/__init__.py
eis/claim/model/__init__.py
eis/claim/model/claim_class.py
eis/claim/model/claim_partner_class.py
eis/claim/model/claim_partner_role_class.py
eis/claim/model/claim_status_class.py
eis/claim/model/create_claim_partner_request_dto.py
eis/claim/model/create_claim_partner_response_class.py
eis/claim/model/create_claim_partner_role_request_dto.py
eis/claim/model/create_claim_partner_role_response_class.py
eis/claim/model/create_claim_request_dto.py
eis/claim/model/create_claim_response_class.py
eis/claim/model/create_claim_status_request_dto.py
eis/claim/model/create_claim_status_response_class.py
eis/claim/model/create_regulation_item_request_dto.py
eis/claim/model/create_settlement_request_dto.py
eis/claim/model/create_settlement_response_class.py
eis/claim/model/get_claim_partner_response_class.py
eis/claim/model/get_claim_partner_role_response_class.py
eis/claim/model/get_claim_response_class.py
eis/claim/model/get_claim_status_response_class.py
eis/claim/model/get_settlement_response_class.py
eis/claim/model/inline_response200.py
eis/claim/model/inline_response503.py
eis/claim/model/list_claim_partner_roles_response_class.py
eis/claim/model/list_claim_partners_response_class.py
eis/claim/model/list_claim_statuses_response_class.py
eis/claim/model/list_claims_response_class.py
eis/claim/model/list_regulations_response_class.py
eis/claim/model/list_settlements_response_class.py
eis/claim/model/patch_claim_request_dto.py
eis/claim/model/patch_claim_response_class.py
eis_claims.egg-info/PKG-INFO
eis_claims.egg-info/SOURCES.txt
eis_claims.egg-info/dependency_links.txt
eis_claims.egg-info/requires.txt
eis_claims.egg-info/top_level.txt
