Metadata-Version: 2.1
Name: eis-claims
Version: 1.37.0
Summary: EMIL ClaimService
Home-page: UNKNOWN
Author: Contact us
Author-email: kontakt@emil.de
License: UNKNOWN
Keywords: OpenAPI,OpenAPI-Generator,EMIL ClaimService
Platform: UNKNOWN
Requires-Python: >=3.6
